sionna/__init__.py
sionna/phy/__init__.py
sionna/phy/block.py
sionna/phy/config.py
sionna/phy/constants.py
sionna/phy/mapping.py
sionna/phy/channel/__init__.py
sionna/phy/channel/apply_ofdm_channel.py
sionna/phy/channel/apply_time_channel.py
sionna/phy/channel/awgn.py
sionna/phy/channel/channel_model.py
sionna/phy/channel/cir_dataset.py
sionna/phy/channel/constants.py
sionna/phy/channel/discrete_channel.py
sionna/phy/channel/flat_fading_channel.py
sionna/phy/channel/generate_ofdm_channel.py
sionna/phy/channel/generate_time_channel.py
sionna/phy/channel/ofdm_channel.py
sionna/phy/channel/rayleigh_block_fading.py
sionna/phy/channel/spatial_correlation.py
sionna/phy/channel/time_channel.py
sionna/phy/channel/utils.py
sionna/phy/channel/optical/__init__.py
sionna/phy/channel/optical/edfa.py
sionna/phy/channel/optical/fiber.py
sionna/phy/channel/tr38901/__init__.py
sionna/phy/channel/tr38901/antenna.py
sionna/phy/channel/tr38901/cdl.py
sionna/phy/channel/tr38901/channel_coefficients.py
sionna/phy/channel/tr38901/lsp.py
sionna/phy/channel/tr38901/rays.py
sionna/phy/channel/tr38901/rma.py
sionna/phy/channel/tr38901/rma_scenario.py
sionna/phy/channel/tr38901/system_level_channel.py
sionna/phy/channel/tr38901/system_level_scenario.py
sionna/phy/channel/tr38901/tdl.py
sionna/phy/channel/tr38901/uma.py
sionna/phy/channel/tr38901/uma_scenario.py
sionna/phy/channel/tr38901/umi.py
sionna/phy/channel/tr38901/umi_scenario.py
sionna/phy/channel/tr38901/models/CDL-A.json
sionna/phy/channel/tr38901/models/CDL-B.json
sionna/phy/channel/tr38901/models/CDL-C.json
sionna/phy/channel/tr38901/models/CDL-D.json
sionna/phy/channel/tr38901/models/CDL-E.json
sionna/phy/channel/tr38901/models/RMa_LoS.json
sionna/phy/channel/tr38901/models/RMa_NLoS.json
sionna/phy/channel/tr38901/models/RMa_O2I.json
sionna/phy/channel/tr38901/models/TDL-A.json
sionna/phy/channel/tr38901/models/TDL-A30.json
sionna/phy/channel/tr38901/models/TDL-B.json
sionna/phy/channel/tr38901/models/TDL-B100.json
sionna_no_rt-1.2.1.dist-info/licenses/LICENSE
sionna_no_rt-1.2.1.dist-info/METADATA
sionna_no_rt-1.2.1.dist-info/WHEEL
sionna_no_rt-1.2.1.dist-info/top_level.txt
sionna_no_rt-1.2.1.dist-info/RECORD
